{
  "note": "SNU 공통교육과정 교과목 코드 접두사 → 세부영역(fine-area). sbjt_cd의 '.' 앞부분으로 조회. 출처: 2026-1 기초교양 수강편람 p24~. 2025학년도부터 F/C/V/E 체계; 2014~2024 = L04xx; 2014 이전 = 0xx.",
  "codes": {
    "F11": "writing", "F12": "writing",
    "F21": "foreign", "F22": "foreign", "F23": "foreign", "F24": "foreign", "F25": "foreign",
    "F26": "foreign", "F27": "foreign", "F28": "foreign", "F29": "foreign",
    "F31": "math", "F32": "stat", "F33": "physics", "F34": "chem", "F35": "bio", "F36": "earth", "F37": "computing",
    "C10": "culture", "C20": "history", "C30": "human", "C40": "scisense",
    "V10": "veritas", "V20": "veritas", "V30": "veritas",
    "E11": "x_knowledge", "E12": "x_knowledge", "E20": "x_engage",
    "E31": "x_creative", "E32": "x_creative", "E41": "x_arts", "E42": "x_arts", "E43": "x_arts",
    "E51": "x_seminar", "E52": "x_seminar",

    "L0440": "writing", "L0441": "foreign", "L0442": "math", "L0443": "science", "L0444": "computing",
    "L0545": "culture", "L0546": "history", "L0547": "human", "L0549": "scisense", "L0550": "scisense", "L0551": "scisense",
    "L0655": "veritas",
    "L0652": "x_knowledge", "L0653": "x_engage", "L0654": "x_creative", "L0656": "x_arts",

    "031": "writing", "032": "foreign", "033": "math", "034": "science", "035": "computing",
    "041": "culture", "042": "history", "043": "human", "044": "human", "045": "scisense", "046": "scisense", "047": "scisense",
    "051": "x_knowledge", "052": "x_engage", "053": "x_creative", "054": "x_arts", "055": "x_seminar"
  },
  "exceptions": {
    "_note": "sbjt_cd → fine-area, for courses needing finer split than the prefix. Takes priority over `codes`. sbjt_cd matches catalog number exactly (verified vs class data, e.g. 'E52.103').",
    "E52.103": "x_classics",
    "E52.104": "x_classics"
  },
  "gwonjang_note": "학문의 세계 '권장과목(*)' 코드 목록 (2024 기초교양 수강편람 기준, 44과목). 사범대·생활대·수의대 비고 '언어와문학·문화와예술·역사와철학 권장과목(*) 중 1과목 필수'에 사용. 자문/비강제(advisory) — 2021~2023 입학생은 일부 차이 가능, 직접 확인. 범례상 46이라 표기되나 실제 코드 44개.",
  "gwonjang_codes": [
    "041.004", "L0545.000500", "L0545.000600", "L0545.000700", "041.019", "041.021", "041.022", "041.023", "L0545.001000", "041.025", "L0545.002500", "041.029", "041.032", "041.033", "041.035", "041.037", "041.038", "041.040",
    "042.005", "042.007", "042.009", "042.011", "042.013", "042.016",
    "L0547.001200", "043.003", "043.004", "L0547.001000", "043.006", "L0547.000300", "L0547.000400", "L0547.001800", "L0547.001900", "043.028", "043.029", "043.041", "043.047", "043.048", "043.049", "L0547.002900", "043.074", "043.075", "043.076", "043.083"
  ],
  "junggeup_note": "제2외국어 '중급 이상' 과목 코드 목록 (2024 기초교양 수강편람 기준, 41과목). 인문대 외국어 비고 '제2외국어 9학점 중 중급 이상 1과목 포함'에 사용. 자문/비강제(advisory) — 초급/입문/'1'단계 과목 제외. 2021~2023 입학생 일부 차이 가능, 직접 확인.",
  "junggeup_codes": [
    "032.007", "032.008", "032.009", "032.012", "032.013", "032.014", "032.015", "032.016", "032.029", "032.030", "032.031", "032.033", "032.036", "032.037", "032.038", "L0441.000300", "032.040", "032.043", "032.044", "032.045", "032.046", "032.047", "032.050", "032.051", "032.052", "032.053", "032.054", "032.056", "032.058", "032.068", "032.070", "032.060", "032.074", "032.076", "032.072", "032.064", "032.065", "032.066", "032.078", "032.080", "L0441.000500"
  ]
}
